riscvm/__init__.py
riscvm/__main__.py
riscvm/bus.py
riscvm/cpu.py
riscvm/disasm.py
riscvm/emulator.py
riscvm/exception.py
riscvm/instruction.py
riscvm/mport.py
riscvm/ram.py
riscvm/rangemanager.py
riscvm/register.py
riscvm/utils.py
tests/__init__.py
tests/asm.py
tests/riscv32i_test.py
tests/test_instruction.py
tests/test_mem.py
riscvm-0.1.1.dist-info/METADATA
riscvm-0.1.1.dist-info/WHEEL
riscvm-0.1.1.dist-info/top_level.txt
riscvm-0.1.1.dist-info/RECORD
